MANIFEST.in
README.rmd
setup.py
my_names/__init__.py
my_names/get_names.py
my_names/bin/get_names.bat
my_names_lib_x.egg-info/PKG-INFO
my_names_lib_x.egg-info/SOURCES.txt
my_names_lib_x.egg-info/dependency_links.txt
my_names_lib_x.egg-info/top_level.txt