Metadata-Version: 1.0
Name: my-names-lib-x
Version: 1.0
Summary: Generate random names with length
Home-page: https://github.com
Author: mmm
Author-email: mmm@Company.com
License: UNKNOWN
Keywords: random.names
Platform: UNKNOWN
